odoo/addons/web_widget_image_download/README.rst
odoo/addons/web_widget_image_download/__init__.py
odoo/addons/web_widget_image_download/__manifest__.py
odoo/addons/web_widget_image_download/i18n/hr.po
odoo/addons/web_widget_image_download/i18n/lt.po
odoo/addons/web_widget_image_download/i18n/nl_NL.po
odoo/addons/web_widget_image_download/i18n/web_widget_image_download.pot
odoo/addons/web_widget_image_download/readme/CONTRIBUTORS.rst
odoo/addons/web_widget_image_download/readme/DESCRIPTION.rst
odoo/addons/web_widget_image_download/readme/USAGE.rst
odoo/addons/web_widget_image_download/static/description/icon.png
odoo/addons/web_widget_image_download/static/description/index.html
odoo/addons/web_widget_image_download/static/src/css/web_widget_image_download.css
odoo/addons/web_widget_image_download/static/src/js/web_widget_image_download.js
odoo/addons/web_widget_image_download/static/src/xml/web_widget_image_download.xml
odoo/addons/web_widget_image_download/views/assets.xml
odoo11_addon_web_widget_image_download-11.0.1.0.0.99.dev6.dist-info/METADATA
odoo11_addon_web_widget_image_download-11.0.1.0.0.99.dev6.dist-info/WHEEL
odoo11_addon_web_widget_image_download-11.0.1.0.0.99.dev6.dist-info/top_level.txt
odoo11_addon_web_widget_image_download-11.0.1.0.0.99.dev6.dist-info/RECORD
